<?xml version="1.0" encoding="UTF-8" ?>
<!DOCTYPE mapper PUBLIC "-//mybatis.org//DTD Mapper 3.0//EN" "http://mybatis.org/dtd/mybatis-3-mapper.dtd" >
<mapper namespace="com.zebone.dip.ws.resource.dao.PResourceUserLogMapper" >
  <resultMap id="BaseResultMap" type="com.zebone.dip.ws.resource.model.PResourceUserLog" >
    <!--
      WARNING - @mbggenerated
      This element is automatically generated by MyBatis Generator, do not modify.
      This element was generated on Mon Mar 31 08:42:14 CST 2014.
    -->
    <id column="ID_" property="id" jdbcType="VARCHAR" />
    <result column="U_ID" property="uId" jdbcType="VARCHAR" />
    <result column="CODE" property="code" jdbcType="VARCHAR" />
    <result column="NAME" property="name" jdbcType="VARCHAR" />
    <result column="ALIAS" property="alias" jdbcType="VARCHAR" />
    <result column="ID_TYPE_CODE" property="idTypeCode" jdbcType="VARCHAR" />
    <result column="ID_NO" property="idNo" jdbcType="VARCHAR" />
    <result column="MEDICAL_ORGAN_CODE" property="medicalOrganCode" jdbcType="VARCHAR" />
    <result column="SEX_CODE" property="sexCode" jdbcType="VARCHAR" />
    <result column="NATIONALITY_CODE" property="nationalityCode" jdbcType="VARCHAR" />
    <result column="NATION_CODE" property="nationCode" jdbcType="VARCHAR" />
    <result column="NATIVE_PLACE" property="nativePlace" jdbcType="VARCHAR" />
    <result column="BIRTHDAY" property="birthday" jdbcType="VARCHAR" />
    <result column="MARITAL_STATUS_CODE" property="maritalStatusCode" jdbcType="VARCHAR" />
    <result column="DEPARTMENT_CODE" property="departmentCode" jdbcType="VARCHAR" />
    <result column="JOB_CATEGORY_CODE" property="jobCategoryCode" jdbcType="VARCHAR" />
    <result column="POST_CODE" property="postCode" jdbcType="VARCHAR" />
    <result column="POSITIONAL_TITLES_CODE" property="positionalTitlesCode" jdbcType="VARCHAR" />
    <result column="POLITICAL_STATUS_CODE" property="politicalStatusCode" jdbcType="VARCHAR" />
    <result column="ADDRESS_CODE" property="addressCode" jdbcType="VARCHAR" />
    <result column="ADDRESS" property="address" jdbcType="VARCHAR" />
    <result column="TEL" property="tel" jdbcType="VARCHAR" />
    <result column="MOBILE" property="mobile" jdbcType="VARCHAR" />
    <result column="EMAIL" property="email" jdbcType="VARCHAR" />
    <result column="QQ" property="qq" jdbcType="VARCHAR" />
    <result column="MSN" property="msn" jdbcType="VARCHAR" />
    <result column="ENTRY_DATE" property="entryDate" jdbcType="VARCHAR" />
    <result column="QUALIFICATION_DATE" property="qualificationDate" jdbcType="VARCHAR" />
    <result column="EXAM_SOURCE" property="examSource" jdbcType="DECIMAL" />
    <result column="CERTIFICATE_NO" property="certificateNo" jdbcType="VARCHAR" />
    <result column="SCHOOL" property="school" jdbcType="VARCHAR" />
    <result column="PROFESSION" property="profession" jdbcType="VARCHAR" />
    <result column="EDUCATION" property="education" jdbcType="VARCHAR" />
    <result column="DEGREE" property="degree" jdbcType="VARCHAR" />
    <result column="DIPLOMA_NO" property="diplomaNo" jdbcType="VARCHAR" />
    <result column="DEGREE_CERTIFICATE_NO" property="degreeCertificateNo" jdbcType="VARCHAR" />
    <result column="GRADUATION_DATE" property="graduationDate" jdbcType="VARCHAR" />
    <result column="SCHOOL_SYSTEM" property="schoolSystem" jdbcType="VARCHAR" />
    <result column="HEALTH_CONDITION" property="healthCondition" jdbcType="VARCHAR" />
    <result column="FIRST_WORK_DATE" property="firstWorkDate" jdbcType="VARCHAR" />
    <result column="RESUME" property="resume" jdbcType="VARCHAR" />
    <result column="OPER_TYPE" property="operType" jdbcType="VARCHAR" />
    <result column="CREATE_TIME" property="createTime" jdbcType="VARCHAR" />
    <result column="INPUT_ORG_CODE" property="inputOrgCode" jdbcType="VARCHAR" />
    <result column="INPUT_USER_CODE" property="inputUserCode" jdbcType="VARCHAR" />
  </resultMap>
  <sql id="Example_Where_Clause" >
    <!--
      WARNING - @mbggenerated
      This element is automatically generated by MyBatis Generator, do not modify.
      This element was generated on Mon Mar 31 08:42:14 CST 2014.
    -->
    <where >
      <foreach collection="oredCriteria" item="criteria" separator="or" >
        <if test="criteria.valid" >
          <trim prefix="(" suffix=")" prefixOverrides="and" >
            <foreach collection="criteria.criteria" item="criterion" >
              <choose >
                <when test="criterion.noValue" >
                  and ${criterion.condition}
                </when>
                <when test="criterion.singleValue" >
                  and ${criterion.condition} #{criterion.value}
                </when>
                <when test="criterion.betweenValue" >
                  and ${criterion.condition} #{criterion.value} and #{criterion.secondValue}
                </when>
                <when test="criterion.listValue" >
                  and ${criterion.condition}
                  <foreach collection="criterion.value" item="listItem" open="(" close=")" separator="," >
                    #{listItem}
                  </foreach>
                </when>
              </choose>
            </foreach>
          </trim>
        </if>
      </foreach>
    </where>
  </sql>
  <sql id="Update_By_Example_Where_Clause" >
    <!--
      WARNING - @mbggenerated
      This element is automatically generated by MyBatis Generator, do not modify.
      This element was generated on Mon Mar 31 08:42:14 CST 2014.
    -->
    <where >
      <foreach collection="example.oredCriteria" item="criteria" separator="or" >
        <if test="criteria.valid" >
          <trim prefix="(" suffix=")" prefixOverrides="and" >
            <foreach collection="criteria.criteria" item="criterion" >
              <choose >
                <when test="criterion.noValue" >
                  and ${criterion.condition}
                </when>
                <when test="criterion.singleValue" >
                  and ${criterion.condition} #{criterion.value}
                </when>
                <when test="criterion.betweenValue" >
                  and ${criterion.condition} #{criterion.value} and #{criterion.secondValue}
                </when>
                <when test="criterion.listValue" >
                  and ${criterion.condition}
                  <foreach collection="criterion.value" item="listItem" open="(" close=")" separator="," >
                    #{listItem}
                  </foreach>
                </when>
              </choose>
            </foreach>
          </trim>
        </if>
      </foreach>
    </where>
  </sql>
  <sql id="Base_Column_List" >
    <!--
      WARNING - @mbggenerated
      This element is automatically generated by MyBatis Generator, do not modify.
      This element was generated on Mon Mar 31 08:42:14 CST 2014.
    -->
    ID_, U_ID, CODE, NAME, ALIAS, ID_TYPE_CODE, ID_NO, MEDICAL_ORGAN_CODE, SEX_CODE, 
    NATIONALITY_CODE, NATION_CODE, NATIVE_PLACE, BIRTHDAY, MARITAL_STATUS_CODE, DEPARTMENT_CODE, 
    JOB_CATEGORY_CODE, POST_CODE, POSITIONAL_TITLES_CODE, POLITICAL_STATUS_CODE, ADDRESS_CODE, 
    ADDRESS, TEL, MOBILE, EMAIL, QQ, MSN, ENTRY_DATE, QUALIFICATION_DATE, EXAM_SOURCE, 
    CERTIFICATE_NO, SCHOOL, PROFESSION, EDUCATION, DEGREE, DIPLOMA_NO, DEGREE_CERTIFICATE_NO, 
    GRADUATION_DATE, SCHOOL_SYSTEM, HEALTH_CONDITION, FIRST_WORK_DATE, RESUME, OPER_TYPE, 
    CREATE_TIME, INPUT_ORG_CODE, INPUT_USER_CODE
  </sql>
  <select id="selectByExample" resultMap="BaseResultMap" parameterType="com.zebone.dip.ws.resource.model.PResourceUserLogExample" >
    <!--
      WARNING - @mbggenerated
      This element is automatically generated by MyBatis Generator, do not modify.
      This element was generated on Mon Mar 31 08:42:14 CST 2014.
    -->
    select
    <if test="distinct" >
      distinct
    </if>
    <include refid="Base_Column_List" />
    from P_RESOURCE_USER_LOG
    <if test="_parameter != null" >
      <include refid="Example_Where_Clause" />
    </if>
    <if test="orderByClause != null" >
      order by ${orderByClause}
    </if>
  </select>
  <select id="selectByPrimaryKey" resultMap="BaseResultMap" parameterType="java.lang.String" >
    <!--
      WARNING - @mbggenerated
      This element is automatically generated by MyBatis Generator, do not modify.
      This element was generated on Mon Mar 31 08:42:14 CST 2014.
    -->
    select 
    <include refid="Base_Column_List" />
    from P_RESOURCE_USER_LOG
    where ID_ = #{id,jdbcType=VARCHAR}
  </select>
  <delete id="deleteByPrimaryKey" parameterType="java.lang.String" >
    <!--
      WARNING - @mbggenerated
      This element is automatically generated by MyBatis Generator, do not modify.
      This element was generated on Mon Mar 31 08:42:14 CST 2014.
    -->
    delete from P_RESOURCE_USER_LOG
    where ID_ = #{id,jdbcType=VARCHAR}
  </delete>
  <delete id="deleteByExample" parameterType="com.zebone.dip.ws.resource.model.PResourceUserLogExample" >
    <!--
      WARNING - @mbggenerated
      This element is automatically generated by MyBatis Generator, do not modify.
      This element was generated on Mon Mar 31 08:42:14 CST 2014.
    -->
    delete from P_RESOURCE_USER_LOG
    <if test="_parameter != null" >
      <include refid="Example_Where_Clause" />
    </if>
  </delete>
  <insert id="insert" parameterType="com.zebone.dip.ws.resource.model.PResourceUserLog" >
    <!--
      WARNING - @mbggenerated
      This element is automatically generated by MyBatis Generator, do not modify.
      This element was generated on Mon Mar 31 08:42:14 CST 2014.
    -->
    insert into P_RESOURCE_USER_LOG (ID_, U_ID, CODE, 
      NAME, ALIAS, ID_TYPE_CODE, 
      ID_NO, MEDICAL_ORGAN_CODE, SEX_CODE, 
      NATIONALITY_CODE, NATION_CODE, NATIVE_PLACE, 
      BIRTHDAY, MARITAL_STATUS_CODE, DEPARTMENT_CODE, 
      JOB_CATEGORY_CODE, POST_CODE, POSITIONAL_TITLES_CODE, 
      POLITICAL_STATUS_CODE, ADDRESS_CODE, ADDRESS, 
      TEL, MOBILE, EMAIL, 
      QQ, MSN, ENTRY_DATE, 
      QUALIFICATION_DATE, EXAM_SOURCE, CERTIFICATE_NO, 
      SCHOOL, PROFESSION, EDUCATION, 
      DEGREE, DIPLOMA_NO, DEGREE_CERTIFICATE_NO, 
      GRADUATION_DATE, SCHOOL_SYSTEM, HEALTH_CONDITION, 
      FIRST_WORK_DATE, RESUME, OPER_TYPE, 
      CREATE_TIME, INPUT_ORG_CODE, INPUT_USER_CODE
      )
    values (#{id,jdbcType=VARCHAR}, #{uId,jdbcType=VARCHAR}, #{code,jdbcType=VARCHAR}, 
      #{name,jdbcType=VARCHAR}, #{alias,jdbcType=VARCHAR}, #{idTypeCode,jdbcType=VARCHAR}, 
      #{idNo,jdbcType=VARCHAR}, #{medicalOrganCode,jdbcType=VARCHAR}, #{sexCode,jdbcType=VARCHAR}, 
      #{nationalityCode,jdbcType=VARCHAR}, #{nationCode,jdbcType=VARCHAR}, #{nativePlace,jdbcType=VARCHAR}, 
      #{birthday,jdbcType=VARCHAR}, #{maritalStatusCode,jdbcType=VARCHAR}, #{departmentCode,jdbcType=VARCHAR}, 
      #{jobCategoryCode,jdbcType=VARCHAR}, #{postCode,jdbcType=VARCHAR}, #{positionalTitlesCode,jdbcType=VARCHAR}, 
      #{politicalStatusCode,jdbcType=VARCHAR}, #{addressCode,jdbcType=VARCHAR}, #{address,jdbcType=VARCHAR}, 
      #{tel,jdbcType=VARCHAR}, #{mobile,jdbcType=VARCHAR}, #{email,jdbcType=VARCHAR}, 
      #{qq,jdbcType=VARCHAR}, #{msn,jdbcType=VARCHAR}, #{entryDate,jdbcType=VARCHAR}, 
      #{qualificationDate,jdbcType=VARCHAR}, #{examSource,jdbcType=DECIMAL}, #{certificateNo,jdbcType=VARCHAR}, 
      #{school,jdbcType=VARCHAR}, #{profession,jdbcType=VARCHAR}, #{education,jdbcType=VARCHAR}, 
      #{degree,jdbcType=VARCHAR}, #{diplomaNo,jdbcType=VARCHAR}, #{degreeCertificateNo,jdbcType=VARCHAR}, 
      #{graduationDate,jdbcType=VARCHAR}, #{schoolSystem,jdbcType=VARCHAR}, #{healthCondition,jdbcType=VARCHAR}, 
      #{firstWorkDate,jdbcType=VARCHAR}, #{resume,jdbcType=VARCHAR}, #{operType,jdbcType=VARCHAR}, 
      #{createTime,jdbcType=VARCHAR}, #{inputOrgCode,jdbcType=VARCHAR}, #{inputUserCode,jdbcType=VARCHAR}
      )
  </insert>
  <insert id="insertSelective" parameterType="com.zebone.dip.ws.resource.model.PResourceUserLog" >
    <!--
      WARNING - @mbggenerated
      This element is automatically generated by MyBatis Generator, do not modify.
      This element was generated on Mon Mar 31 08:42:14 CST 2014.
    -->
    insert into P_RESOURCE_USER_LOG
    <trim prefix="(" suffix=")" suffixOverrides="," >
      <if test="id != null" >
        ID_,
      </if>
      <if test="uId != null" >
        U_ID,
      </if>
      <if test="code != null" >
        CODE,
      </if>
      <if test="name != null" >
        NAME,
      </if>
      <if test="alias != null" >
        ALIAS,
      </if>
      <if test="idTypeCode != null" >
        ID_TYPE_CODE,
      </if>
      <if test="idNo != null" >
        ID_NO,
      </if>
      <if test="medicalOrganCode != null" >
        MEDICAL_ORGAN_CODE,
      </if>
      <if test="sexCode != null" >
        SEX_CODE,
      </if>
      <if test="nationalityCode != null" >
        NATIONALITY_CODE,
      </if>
      <if test="nationCode != null" >
        NATION_CODE,
      </if>
      <if test="nativePlace != null" >
        NATIVE_PLACE,
      </if>
      <if test="birthday != null" >
        BIRTHDAY,
      </if>
      <if test="maritalStatusCode != null" >
        MARITAL_STATUS_CODE,
      </if>
      <if test="departmentCode != null" >
        DEPARTMENT_CODE,
      </if>
      <if test="jobCategoryCode != null" >
        JOB_CATEGORY_CODE,
      </if>
      <if test="postCode != null" >
        POST_CODE,
      </if>
      <if test="positionalTitlesCode != null" >
        POSITIONAL_TITLES_CODE,
      </if>
      <if test="politicalStatusCode != null" >
        POLITICAL_STATUS_CODE,
      </if>
      <if test="addressCode != null" >
        ADDRESS_CODE,
      </if>
      <if test="address != null" >
        ADDRESS,
      </if>
      <if test="tel != null" >
        TEL,
      </if>
      <if test="mobile != null" >
        MOBILE,
      </if>
      <if test="email != null" >
        EMAIL,
      </if>
      <if test="qq != null" >
        QQ,
      </if>
      <if test="msn != null" >
        MSN,
      </if>
      <if test="entryDate != null" >
        ENTRY_DATE,
      </if>
      <if test="qualificationDate != null" >
        QUALIFICATION_DATE,
      </if>
      <if test="examSource != null" >
        EXAM_SOURCE,
      </if>
      <if test="certificateNo != null" >
        CERTIFICATE_NO,
      </if>
      <if test="school != null" >
        SCHOOL,
      </if>
      <if test="profession != null" >
        PROFESSION,
      </if>
      <if test="education != null" >
        EDUCATION,
      </if>
      <if test="degree != null" >
        DEGREE,
      </if>
      <if test="diplomaNo != null" >
        DIPLOMA_NO,
      </if>
      <if test="degreeCertificateNo != null" >
        DEGREE_CERTIFICATE_NO,
      </if>
      <if test="graduationDate != null" >
        GRADUATION_DATE,
      </if>
      <if test="schoolSystem != null" >
        SCHOOL_SYSTEM,
      </if>
      <if test="healthCondition != null" >
        HEALTH_CONDITION,
      </if>
      <if test="firstWorkDate != null" >
        FIRST_WORK_DATE,
      </if>
      <if test="resume != null" >
        RESUME,
      </if>
      <if test="operType != null" >
        OPER_TYPE,
      </if>
      <if test="createTime != null" >
        CREATE_TIME,
      </if>
      <if test="inputOrgCode != null" >
        INPUT_ORG_CODE,
      </if>
      <if test="inputUserCode != null" >
        INPUT_USER_CODE,
      </if>
    </trim>
    <trim prefix="values (" suffix=")" suffixOverrides="," >
      <if test="id != null" >
        #{id,jdbcType=VARCHAR},
      </if>
      <if test="uId != null" >
        #{uId,jdbcType=VARCHAR},
      </if>
      <if test="code != null" >
        #{code,jdbcType=VARCHAR},
      </if>
      <if test="name != null" >
        #{name,jdbcType=VARCHAR},
      </if>
      <if test="alias != null" >
        #{alias,jdbcType=VARCHAR},
      </if>
      <if test="idTypeCode != null" >
        #{idTypeCode,jdbcType=VARCHAR},
      </if>
      <if test="idNo != null" >
        #{idNo,jdbcType=VARCHAR},
      </if>
      <if test="medicalOrganCode != null" >
        #{medicalOrganCode,jdbcType=VARCHAR},
      </if>
      <if test="sexCode != null" >
        #{sexCode,jdbcType=VARCHAR},
      </if>
      <if test="nationalityCode != null" >
        #{nationalityCode,jdbcType=VARCHAR},
      </if>
      <if test="nationCode != null" >
        #{nationCode,jdbcType=VARCHAR},
      </if>
      <if test="nativePlace != null" >
        #{nativePlace,jdbcType=VARCHAR},
      </if>
      <if test="birthday != null" >
        #{birthday,jdbcType=VARCHAR},
      </if>
      <if test="maritalStatusCode != null" >
        #{maritalStatusCode,jdbcType=VARCHAR},
      </if>
      <if test="departmentCode != null" >
        #{departmentCode,jdbcType=VARCHAR},
      </if>
      <if test="jobCategoryCode != null" >
        #{jobCategoryCode,jdbcType=VARCHAR},
      </if>
      <if test="postCode != null" >
        #{postCode,jdbcType=VARCHAR},
      </if>
      <if test="positionalTitlesCode != null" >
        #{positionalTitlesCode,jdbcType=VARCHAR},
      </if>
      <if test="politicalStatusCode != null" >
        #{politicalStatusCode,jdbcType=VARCHAR},
      </if>
      <if test="addressCode != null" >
        #{addressCode,jdbcType=VARCHAR},
      </if>
      <if test="address != null" >
        #{address,jdbcType=VARCHAR},
      </if>
      <if test="tel != null" >
        #{tel,jdbcType=VARCHAR},
      </if>
      <if test="mobile != null" >
        #{mobile,jdbcType=VARCHAR},
      </if>
      <if test="email != null" >
        #{email,jdbcType=VARCHAR},
      </if>
      <if test="qq != null" >
        #{qq,jdbcType=VARCHAR},
      </if>
      <if test="msn != null" >
        #{msn,jdbcType=VARCHAR},
      </if>
      <if test="entryDate != null" >
        #{entryDate,jdbcType=VARCHAR},
      </if>
      <if test="qualificationDate != null" >
        #{qualificationDate,jdbcType=VARCHAR},
      </if>
      <if test="examSource != null" >
        #{examSource,jdbcType=DECIMAL},
      </if>
      <if test="certificateNo != null" >
        #{certificateNo,jdbcType=VARCHAR},
      </if>
      <if test="school != null" >
        #{school,jdbcType=VARCHAR},
      </if>
      <if test="profession != null" >
        #{profession,jdbcType=VARCHAR},
      </if>
      <if test="education != null" >
        #{education,jdbcType=VARCHAR},
      </if>
      <if test="degree != null" >
        #{degree,jdbcType=VARCHAR},
      </if>
      <if test="diplomaNo != null" >
        #{diplomaNo,jdbcType=VARCHAR},
      </if>
      <if test="degreeCertificateNo != null" >
        #{degreeCertificateNo,jdbcType=VARCHAR},
      </if>
      <if test="graduationDate != null" >
        #{graduationDate,jdbcType=VARCHAR},
      </if>
      <if test="schoolSystem != null" >
        #{schoolSystem,jdbcType=VARCHAR},
      </if>
      <if test="healthCondition != null" >
        #{healthCondition,jdbcType=VARCHAR},
      </if>
      <if test="firstWorkDate != null" >
        #{firstWorkDate,jdbcType=VARCHAR},
      </if>
      <if test="resume != null" >
        #{resume,jdbcType=VARCHAR},
      </if>
      <if test="operType != null" >
        #{operType,jdbcType=VARCHAR},
      </if>
      <if test="createTime != null" >
        #{createTime,jdbcType=VARCHAR},
      </if>
      <if test="inputOrgCode != null" >
        #{inputOrgCode,jdbcType=VARCHAR},
      </if>
      <if test="inputUserCode != null" >
        #{inputUserCode,jdbcType=VARCHAR},
      </if>
    </trim>
  </insert>
  <select id="countByExample" parameterType="com.zebone.dip.ws.resource.model.PResourceUserLogExample" resultType="java.lang.Integer" >
    <!--
      WARNING - @mbggenerated
      This element is automatically generated by MyBatis Generator, do not modify.
      This element was generated on Mon Mar 31 08:42:14 CST 2014.
    -->
    select count(*) from P_RESOURCE_USER_LOG
    <if test="_parameter != null" >
      <include refid="Example_Where_Clause" />
    </if>
  </select>
  <update id="updateByExampleSelective" parameterType="map" >
    <!--
      WARNING - @mbggenerated
      This element is automatically generated by MyBatis Generator, do not modify.
      This element was generated on Mon Mar 31 08:42:14 CST 2014.
    -->
    update P_RESOURCE_USER_LOG
    <set >
      <if test="record.id != null" >
        ID_ = #{record.id,jdbcType=VARCHAR},
      </if>
      <if test="record.uId != null" >
        U_ID = #{record.uId,jdbcType=VARCHAR},
      </if>
      <if test="record.code != null" >
        CODE = #{record.code,jdbcType=VARCHAR},
      </if>
      <if test="record.name != null" >
        NAME = #{record.name,jdbcType=VARCHAR},
      </if>
      <if test="record.alias != null" >
        ALIAS = #{record.alias,jdbcType=VARCHAR},
      </if>
      <if test="record.idTypeCode != null" >
        ID_TYPE_CODE = #{record.idTypeCode,jdbcType=VARCHAR},
      </if>
      <if test="record.idNo != null" >
        ID_NO = #{record.idNo,jdbcType=VARCHAR},
      </if>
      <if test="record.medicalOrganCode != null" >
        MEDICAL_ORGAN_CODE = #{record.medicalOrganCode,jdbcType=VARCHAR},
      </if>
      <if test="record.sexCode != null" >
        SEX_CODE = #{record.sexCode,jdbcType=VARCHAR},
      </if>
      <if test="record.nationalityCode != null" >
        NATIONALITY_CODE = #{record.nationalityCode,jdbcType=VARCHAR},
      </if>
      <if test="record.nationCode != null" >
        NATION_CODE = #{record.nationCode,jdbcType=VARCHAR},
      </if>
      <if test="record.nativePlace != null" >
        NATIVE_PLACE = #{record.nativePlace,jdbcType=VARCHAR},
      </if>
      <if test="record.birthday != null" >
        BIRTHDAY = #{record.birthday,jdbcType=VARCHAR},
      </if>
      <if test="record.maritalStatusCode != null" >
        MARITAL_STATUS_CODE = #{record.maritalStatusCode,jdbcType=VARCHAR},
      </if>
      <if test="record.departmentCode != null" >
        DEPARTMENT_CODE = #{record.departmentCode,jdbcType=VARCHAR},
      </if>
      <if test="record.jobCategoryCode != null" >
        JOB_CATEGORY_CODE = #{record.jobCategoryCode,jdbcType=VARCHAR},
      </if>
      <if test="record.postCode != null" >
        POST_CODE = #{record.postCode,jdbcType=VARCHAR},
      </if>
      <if test="record.positionalTitlesCode != null" >
        POSITIONAL_TITLES_CODE = #{record.positionalTitlesCode,jdbcType=VARCHAR},
      </if>
      <if test="record.politicalStatusCode != null" >
        POLITICAL_STATUS_CODE = #{record.politicalStatusCode,jdbcType=VARCHAR},
      </if>
      <if test="record.addressCode != null" >
        ADDRESS_CODE = #{record.addressCode,jdbcType=VARCHAR},
      </if>
      <if test="record.address != null" >
        ADDRESS = #{record.address,jdbcType=VARCHAR},
      </if>
      <if test="record.tel != null" >
        TEL = #{record.tel,jdbcType=VARCHAR},
      </if>
      <if test="record.mobile != null" >
        MOBILE = #{record.mobile,jdbcType=VARCHAR},
      </if>
      <if test="record.email != null" >
        EMAIL = #{record.email,jdbcType=VARCHAR},
      </if>
      <if test="record.qq != null" >
        QQ = #{record.qq,jdbcType=VARCHAR},
      </if>
      <if test="record.msn != null" >
        MSN = #{record.msn,jdbcType=VARCHAR},
      </if>
      <if test="record.entryDate != null" >
        ENTRY_DATE = #{record.entryDate,jdbcType=VARCHAR},
      </if>
      <if test="record.qualificationDate != null" >
        QUALIFICATION_DATE = #{record.qualificationDate,jdbcType=VARCHAR},
      </if>
      <if test="record.examSource != null" >
        EXAM_SOURCE = #{record.examSource,jdbcType=DECIMAL},
      </if>
      <if test="record.certificateNo != null" >
        CERTIFICATE_NO = #{record.certificateNo,jdbcType=VARCHAR},
      </if>
      <if test="record.school != null" >
        SCHOOL = #{record.school,jdbcType=VARCHAR},
      </if>
      <if test="record.profession != null" >
        PROFESSION = #{record.profession,jdbcType=VARCHAR},
      </if>
      <if test="record.education != null" >
        EDUCATION = #{record.education,jdbcType=VARCHAR},
      </if>
      <if test="record.degree != null" >
        DEGREE = #{record.degree,jdbcType=VARCHAR},
      </if>
      <if test="record.diplomaNo != null" >
        DIPLOMA_NO = #{record.diplomaNo,jdbcType=VARCHAR},
      </if>
      <if test="record.degreeCertificateNo != null" >
        DEGREE_CERTIFICATE_NO = #{record.degreeCertificateNo,jdbcType=VARCHAR},
      </if>
      <if test="record.graduationDate != null" >
        GRADUATION_DATE = #{record.graduationDate,jdbcType=VARCHAR},
      </if>
      <if test="record.schoolSystem != null" >
        SCHOOL_SYSTEM = #{record.schoolSystem,jdbcType=VARCHAR},
      </if>
      <if test="record.healthCondition != null" >
        HEALTH_CONDITION = #{record.healthCondition,jdbcType=VARCHAR},
      </if>
      <if test="record.firstWorkDate != null" >
        FIRST_WORK_DATE = #{record.firstWorkDate,jdbcType=VARCHAR},
      </if>
      <if test="record.resume != null" >
        RESUME = #{record.resume,jdbcType=VARCHAR},
      </if>
      <if test="record.operType != null" >
        OPER_TYPE = #{record.operType,jdbcType=VARCHAR},
      </if>
      <if test="record.createTime != null" >
        CREATE_TIME = #{record.createTime,jdbcType=VARCHAR},
      </if>
      <if test="record.inputOrgCode != null" >
        INPUT_ORG_CODE = #{record.inputOrgCode,jdbcType=VARCHAR},
      </if>
      <if test="record.inputUserCode != null" >
        INPUT_USER_CODE = #{record.inputUserCode,jdbcType=VARCHAR},
      </if>
    </set>
    <if test="_parameter != null" >
      <include refid="Update_By_Example_Where_Clause" />
    </if>
  </update>
  <update id="updateByExample" parameterType="map" >
    <!--
      WARNING - @mbggenerated
      This element is automatically generated by MyBatis Generator, do not modify.
      This element was generated on Mon Mar 31 08:42:14 CST 2014.
    -->
    update P_RESOURCE_USER_LOG
    set ID_ = #{record.id,jdbcType=VARCHAR},
      U_ID = #{record.uId,jdbcType=VARCHAR},
      CODE = #{record.code,jdbcType=VARCHAR},
      NAME = #{record.name,jdbcType=VARCHAR},
      ALIAS = #{record.alias,jdbcType=VARCHAR},
      ID_TYPE_CODE = #{record.idTypeCode,jdbcType=VARCHAR},
      ID_NO = #{record.idNo,jdbcType=VARCHAR},
      MEDICAL_ORGAN_CODE = #{record.medicalOrganCode,jdbcType=VARCHAR},
      SEX_CODE = #{record.sexCode,jdbcType=VARCHAR},
      NATIONALITY_CODE = #{record.nationalityCode,jdbcType=VARCHAR},
      NATION_CODE = #{record.nationCode,jdbcType=VARCHAR},
      NATIVE_PLACE = #{record.nativePlace,jdbcType=VARCHAR},
      BIRTHDAY = #{record.birthday,jdbcType=VARCHAR},
      MARITAL_STATUS_CODE = #{record.maritalStatusCode,jdbcType=VARCHAR},
      DEPARTMENT_CODE = #{record.departmentCode,jdbcType=VARCHAR},
      JOB_CATEGORY_CODE = #{record.jobCategoryCode,jdbcType=VARCHAR},
      POST_CODE = #{record.postCode,jdbcType=VARCHAR},
      POSITIONAL_TITLES_CODE = #{record.positionalTitlesCode,jdbcType=VARCHAR},
      POLITICAL_STATUS_CODE = #{record.politicalStatusCode,jdbcType=VARCHAR},
      ADDRESS_CODE = #{record.addressCode,jdbcType=VARCHAR},
      ADDRESS = #{record.address,jdbcType=VARCHAR},
      TEL = #{record.tel,jdbcType=VARCHAR},
      MOBILE = #{record.mobile,jdbcType=VARCHAR},
      EMAIL = #{record.email,jdbcType=VARCHAR},
      QQ = #{record.qq,jdbcType=VARCHAR},
      MSN = #{record.msn,jdbcType=VARCHAR},
      ENTRY_DATE = #{record.entryDate,jdbcType=VARCHAR},
      QUALIFICATION_DATE = #{record.qualificationDate,jdbcType=VARCHAR},
      EXAM_SOURCE = #{record.examSource,jdbcType=DECIMAL},
      CERTIFICATE_NO = #{record.certificateNo,jdbcType=VARCHAR},
      SCHOOL = #{record.school,jdbcType=VARCHAR},
      PROFESSION = #{record.profession,jdbcType=VARCHAR},
      EDUCATION = #{record.education,jdbcType=VARCHAR},
      DEGREE = #{record.degree,jdbcType=VARCHAR},
      DIPLOMA_NO = #{record.diplomaNo,jdbcType=VARCHAR},
      DEGREE_CERTIFICATE_NO = #{record.degreeCertificateNo,jdbcType=VARCHAR},
      GRADUATION_DATE = #{record.graduationDate,jdbcType=VARCHAR},
      SCHOOL_SYSTEM = #{record.schoolSystem,jdbcType=VARCHAR},
      HEALTH_CONDITION = #{record.healthCondition,jdbcType=VARCHAR},
      FIRST_WORK_DATE = #{record.firstWorkDate,jdbcType=VARCHAR},
      RESUME = #{record.resume,jdbcType=VARCHAR},
      OPER_TYPE = #{record.operType,jdbcType=VARCHAR},
      CREATE_TIME = #{record.createTime,jdbcType=VARCHAR},
      INPUT_ORG_CODE = #{record.inputOrgCode,jdbcType=VARCHAR},
      INPUT_USER_CODE = #{record.inputUserCode,jdbcType=VARCHAR}
    <if test="_parameter != null" >
      <include refid="Update_By_Example_Where_Clause" />
    </if>
  </update>
  <update id="updateByPrimaryKeySelective" parameterType="com.zebone.dip.ws.resource.model.PResourceUserLog" >
    <!--
      WARNING - @mbggenerated
      This element is automatically generated by MyBatis Generator, do not modify.
      This element was generated on Mon Mar 31 08:42:14 CST 2014.
    -->
    update P_RESOURCE_USER_LOG
    <set >
      <if test="uId != null" >
        U_ID = #{uId,jdbcType=VARCHAR},
      </if>
      <if test="code != null" >
        CODE = #{code,jdbcType=VARCHAR},
      </if>
      <if test="name != null" >
        NAME = #{name,jdbcType=VARCHAR},
      </if>
      <if test="alias != null" >
        ALIAS = #{alias,jdbcType=VARCHAR},
      </if>
      <if test="idTypeCode != null" >
        ID_TYPE_CODE = #{idTypeCode,jdbcType=VARCHAR},
      </if>
      <if test="idNo != null" >
        ID_NO = #{idNo,jdbcType=VARCHAR},
      </if>
      <if test="medicalOrganCode != null" >
        MEDICAL_ORGAN_CODE = #{medicalOrganCode,jdbcType=VARCHAR},
      </if>
      <if test="sexCode != null" >
        SEX_CODE = #{sexCode,jdbcType=VARCHAR},
      </if>
      <if test="nationalityCode != null" >
        NATIONALITY_CODE = #{nationalityCode,jdbcType=VARCHAR},
      </if>
      <if test="nationCode != null" >
        NATION_CODE = #{nationCode,jdbcType=VARCHAR},
      </if>
      <if test="nativePlace != null" >
        NATIVE_PLACE = #{nativePlace,jdbcType=VARCHAR},
      </if>
      <if test="birthday != null" >
        BIRTHDAY = #{birthday,jdbcType=VARCHAR},
      </if>
      <if test="maritalStatusCode != null" >
        MARITAL_STATUS_CODE = #{maritalStatusCode,jdbcType=VARCHAR},
      </if>
      <if test="departmentCode != null" >
        DEPARTMENT_CODE = #{departmentCode,jdbcType=VARCHAR},
      </if>
      <if test="jobCategoryCode != null" >
        JOB_CATEGORY_CODE = #{jobCategoryCode,jdbcType=VARCHAR},
      </if>
      <if test="postCode != null" >
        POST_CODE = #{postCode,jdbcType=VARCHAR},
      </if>
      <if test="positionalTitlesCode != null" >
        POSITIONAL_TITLES_CODE = #{positionalTitlesCode,jdbcType=VARCHAR},
      </if>
      <if test="politicalStatusCode != null" >
        POLITICAL_STATUS_CODE = #{politicalStatusCode,jdbcType=VARCHAR},
      </if>
      <if test="addressCode != null" >
        ADDRESS_CODE = #{addressCode,jdbcType=VARCHAR},
      </if>
      <if test="address != null" >
        ADDRESS = #{address,jdbcType=VARCHAR},
      </if>
      <if test="tel != null" >
        TEL = #{tel,jdbcType=VARCHAR},
      </if>
      <if test="mobile != null" >
        MOBILE = #{mobile,jdbcType=VARCHAR},
      </if>
      <if test="email != null" >
        EMAIL = #{email,jdbcType=VARCHAR},
      </if>
      <if test="qq != null" >
        QQ = #{qq,jdbcType=VARCHAR},
      </if>
      <if test="msn != null" >
        MSN = #{msn,jdbcType=VARCHAR},
      </if>
      <if test="entryDate != null" >
        ENTRY_DATE = #{entryDate,jdbcType=VARCHAR},
      </if>
      <if test="qualificationDate != null" >
        QUALIFICATION_DATE = #{qualificationDate,jdbcType=VARCHAR},
      </if>
      <if test="examSource != null" >
        EXAM_SOURCE = #{examSource,jdbcType=DECIMAL},
      </if>
      <if test="certificateNo != null" >
        CERTIFICATE_NO = #{certificateNo,jdbcType=VARCHAR},
      </if>
      <if test="school != null" >
        SCHOOL = #{school,jdbcType=VARCHAR},
      </if>
      <if test="profession != null" >
        PROFESSION = #{profession,jdbcType=VARCHAR},
      </if>
      <if test="education != null" >
        EDUCATION = #{education,jdbcType=VARCHAR},
      </if>
      <if test="degree != null" >
        DEGREE = #{degree,jdbcType=VARCHAR},
      </if>
      <if test="diplomaNo != null" >
        DIPLOMA_NO = #{diplomaNo,jdbcType=VARCHAR},
      </if>
      <if test="degreeCertificateNo != null" >
        DEGREE_CERTIFICATE_NO = #{degreeCertificateNo,jdbcType=VARCHAR},
      </if>
      <if test="graduationDate != null" >
        GRADUATION_DATE = #{graduationDate,jdbcType=VARCHAR},
      </if>
      <if test="schoolSystem != null" >
        SCHOOL_SYSTEM = #{schoolSystem,jdbcType=VARCHAR},
      </if>
      <if test="healthCondition != null" >
        HEALTH_CONDITION = #{healthCondition,jdbcType=VARCHAR},
      </if>
      <if test="firstWorkDate != null" >
        FIRST_WORK_DATE = #{firstWorkDate,jdbcType=VARCHAR},
      </if>
      <if test="resume != null" >
        RESUME = #{resume,jdbcType=VARCHAR},
      </if>
      <if test="operType != null" >
        OPER_TYPE = #{operType,jdbcType=VARCHAR},
      </if>
      <if test="createTime != null" >
        CREATE_TIME = #{createTime,jdbcType=VARCHAR},
      </if>
      <if test="inputOrgCode != null" >
        INPUT_ORG_CODE = #{inputOrgCode,jdbcType=VARCHAR},
      </if>
      <if test="inputUserCode != null" >
        INPUT_USER_CODE = #{inputUserCode,jdbcType=VARCHAR},
      </if>
    </set>
    where ID_ = #{id,jdbcType=VARCHAR}
  </update>
  <update id="updateByPrimaryKey" parameterType="com.zebone.dip.ws.resource.model.PResourceUserLog" >
    <!--
      WARNING - @mbggenerated
      This element is automatically generated by MyBatis Generator, do not modify.
      This element was generated on Mon Mar 31 08:42:14 CST 2014.
    -->
    update P_RESOURCE_USER_LOG
    set U_ID = #{uId,jdbcType=VARCHAR},
      CODE = #{code,jdbcType=VARCHAR},
      NAME = #{name,jdbcType=VARCHAR},
      ALIAS = #{alias,jdbcType=VARCHAR},
      ID_TYPE_CODE = #{idTypeCode,jdbcType=VARCHAR},
      ID_NO = #{idNo,jdbcType=VARCHAR},
      MEDICAL_ORGAN_CODE = #{medicalOrganCode,jdbcType=VARCHAR},
      SEX_CODE = #{sexCode,jdbcType=VARCHAR},
      NATIONALITY_CODE = #{nationalityCode,jdbcType=VARCHAR},
      NATION_CODE = #{nationCode,jdbcType=VARCHAR},
      NATIVE_PLACE = #{nativePlace,jdbcType=VARCHAR},
      BIRTHDAY = #{birthday,jdbcType=VARCHAR},
      MARITAL_STATUS_CODE = #{maritalStatusCode,jdbcType=VARCHAR},
      DEPARTMENT_CODE = #{departmentCode,jdbcType=VARCHAR},
      JOB_CATEGORY_CODE = #{jobCategoryCode,jdbcType=VARCHAR},
      POST_CODE = #{postCode,jdbcType=VARCHAR},
      POSITIONAL_TITLES_CODE = #{positionalTitlesCode,jdbcType=VARCHAR},
      POLITICAL_STATUS_CODE = #{politicalStatusCode,jdbcType=VARCHAR},
      ADDRESS_CODE = #{addressCode,jdbcType=VARCHAR},
      ADDRESS = #{address,jdbcType=VARCHAR},
      TEL = #{tel,jdbcType=VARCHAR},
      MOBILE = #{mobile,jdbcType=VARCHAR},
      EMAIL = #{email,jdbcType=VARCHAR},
      QQ = #{qq,jdbcType=VARCHAR},
      MSN = #{msn,jdbcType=VARCHAR},
      ENTRY_DATE = #{entryDate,jdbcType=VARCHAR},
      QUALIFICATION_DATE = #{qualificationDate,jdbcType=VARCHAR},
      EXAM_SOURCE = #{examSource,jdbcType=DECIMAL},
      CERTIFICATE_NO = #{certificateNo,jdbcType=VARCHAR},
      SCHOOL = #{school,jdbcType=VARCHAR},
      PROFESSION = #{profession,jdbcType=VARCHAR},
      EDUCATION = #{education,jdbcType=VARCHAR},
      DEGREE = #{degree,jdbcType=VARCHAR},
      DIPLOMA_NO = #{diplomaNo,jdbcType=VARCHAR},
      DEGREE_CERTIFICATE_NO = #{degreeCertificateNo,jdbcType=VARCHAR},
      GRADUATION_DATE = #{graduationDate,jdbcType=VARCHAR},
      SCHOOL_SYSTEM = #{schoolSystem,jdbcType=VARCHAR},
      HEALTH_CONDITION = #{healthCondition,jdbcType=VARCHAR},
      FIRST_WORK_DATE = #{firstWorkDate,jdbcType=VARCHAR},
      RESUME = #{resume,jdbcType=VARCHAR},
      OPER_TYPE = #{operType,jdbcType=VARCHAR},
      CREATE_TIME = #{createTime,jdbcType=VARCHAR},
      INPUT_ORG_CODE = #{inputOrgCode,jdbcType=VARCHAR},
      INPUT_USER_CODE = #{inputUserCode,jdbcType=VARCHAR}
    where ID_ = #{id,jdbcType=VARCHAR}
  </update>
</mapper>